[
  {
    "full_name": "rishavanand/github-profilinator",
    "stargazers_count": 648,
    "open_issues_count": 12,
    "forks_count": 60
  },
  {
    "full_name": "Ninad89/joi-relative-date-validator",
    "stargazers_count": 1,
    "open_issues_count": 1,
    "forks_count": 1
  },
  {
    "full_name": "GorvGoyl/Shortcut-Menu-Bar-VSCode-Extension",
    "stargazers_count": 154,
    "open_issues_count": 21,
    "forks_count": 29
  },
  {
    "full_name": "banner-maker/banner-maker",
    "stargazers_count": 129,
    "open_issues_count": 31,
    "forks_count": 22
  },
  {
    "full_name": "Ninad89/express-headers-setter",
    "stargazers_count": 2,
    "open_issues_count": 2,
    "forks_count": 2
  },
  {
    "full_name": "niieani/hashids.js",
    "stargazers_count": 3853,
    "open_issues_count": 14,
    "forks_count": 214
  },
  {
    "full_name": "octokatherine/readme.so",
    "stargazers_count": 3044,
    "open_issues_count": 29,
    "forks_count": 224
  },
  {
    "full_name": "angular/angular-cli",
    "stargazers_count": 25718,
    "open_issues_count": 207,
    "forks_count": 12112
  },
  {
    "full_name": "Polymer/polymer",
    "stargazers_count": 21872,
    "open_issues_count": 52,
    "forks_count": 2028
  },
  {
    "full_name": "JedWatson/classnames",
    "stargazers_count": 16005,
    "open_issues_count": 6,
    "forks_count": 549
  }
]